tarvos/filesystem/__init__.py
tarvos/filesystem/__main__.py
tarvos/filesystem/directory.py
tarvos/filesystem/node.py
tarvos/filesystem/path.py
tarvos/filesystem/file/INI.py
tarvos/filesystem/file/TEXT.py
tarvos/filesystem/file/YAML.py
tarvos/filesystem/file/__init__.py
tarvos/filesystem/file/file.py
tarvos/filesystem/file/archive/GZ.py
tarvos/filesystem/file/archive/TAR.py
tarvos/filesystem/file/archive/ZIP.py
tarvos/filesystem/file/archive/__init__.py
tarvos/filesystem/file/archive/archive.py
tarvos-0.0.2.dist-info/LICENSE
tarvos-0.0.2.dist-info/METADATA
tarvos-0.0.2.dist-info/WHEEL
tarvos-0.0.2.dist-info/top_level.txt
tarvos-0.0.2.dist-info/RECORD
